pkgmon/__init__.py
pkgmon-0.0.1.dist-info/DESCRIPTION.rst
pkgmon-0.0.1.dist-info/METADATA
pkgmon-0.0.1.dist-info/metadata.json
pkgmon-0.0.1.dist-info/RECORD
pkgmon-0.0.1.dist-info/top_level.txt
pkgmon-0.0.1.dist-info/WHEEL
