Metadata-Version: 2.0
Name: pkgmon
Version: 0.0.1
Summary: Utilities to reload and reinstall python packages that are beign observed when changes are detected
Home-page: https://github.com/panyam/pkgmon
Author: Sriram Panyam
Author-email: sri.panyam@gmail.com
License: BSD
Platform: UNKNOWN
Classifier: Development Status :: 2 - Pre-Alpha
Classifier: Intended Audience :: Developers
Classifier: License :: OSI Approved :: BSD License
Classifier: Operating System :: OS Independent
Classifier: Programming Language :: Python
Classifier: Programming Language :: Python :: 2
Classifier: Programming Language :: Python :: 2.7
Classifier: Topic :: Software Development :: Libraries :: Application Frameworks
Classifier: Topic :: Software Development :: Libraries :: Python Modules
Requires-Dist: wheel
Requires-Dist: watchdog
